[
    {
        "password": "mem5162",
        "used": false
    },
    {
        "password": "mem3213",
        "used": false
    },
    {
        "password": "mem3205",
        "used": false
    },
    {
        "password": "mem0531",
        "used": false
    },
    {
        "password": "mem8766",
        "used": false
    },
    {
        "password": "mem5056",
        "used": false
    },
    {
        "password": "mem7844",
        "used": false
    },
    {
        "password": "mem9011",
        "used": false
    },
    {
        "password": "mem2416",
        "used": false
    },
    {
        "password": "mem2825",
        "used": false
    },
    {
        "password": "mem7691",
        "used": false
    },
    {
        "password": "mem4968",
        "used": false
    },
    {
        "password": "mem3176",
        "used": false
    },
    {
        "password": "mem5281",
        "used": false
    },
    {
        "password": "mem9011",
        "used": false
    },
    {
        "password": "mem4513",
        "used": true
    },
    {
        "password": "mem2264",
        "used": true
    },
    {
        "password": "mem4316",
        "used": false
    },
    {
        "password": "mem3624",
        "used": true
    },
    {
        "password": "mem1784",
        "used": false
    },
    {
        "password": "mem7068",
        "used": false
    }
]